calculator/__init__.py
calculator/calculator.py
dkcalculator-1.0.0.dist-info/LICENSE
dkcalculator-1.0.0.dist-info/METADATA
dkcalculator-1.0.0.dist-info/WHEEL
dkcalculator-1.0.0.dist-info/top_level.txt
dkcalculator-1.0.0.dist-info/RECORD
